{
"Changes": [

		/*********
		** Festivals
		*********/	
			/*********
			** Luau Portraits
			*********/

		{
        	"LogName": "Maddie Luau Portraits",			
			"Action": "EditImage",
			"Target": "Portraits/Maddie",
			"FromFile": "{{FirstValidFile: Assets/{{Target}}/Seasonals/Luau_{{MaddiePortraitStyle}}.png, Assets/{{Target}}/{{MaddiePortraitStyle}}.png }}",
			"PatchMode": "Replace",
	        "When": {
                	"DayEvent": "luau",
                	"LocationName": "Beach, temp"                    
                	},
                    	"Update": "OnLocationChange"   
		},

			/*********
			** Luau Sprites
			*********/						
    	{
        	"LogName": "Maddie Luau Sprites",
        	"Action": "EditImage",
        	"Target": "Characters/Maddie",
			"FromFile": "Assets/{{Target}}/Seasonals/Luau_{{TargetWithoutPath}}.png",
			"PatchMode": "Replace",
	        "When": {
            		"DayEvent": "luau",
               		"LocationName": "Beach, temp"                    
               		},
                   		"Update": "OnLocationChange"   		        
    	},

]
}